pakkanpdf/__init__.py
pakkanpdf/core.py
pakkanpdf/exceptions.py
pakkanpdf-0.1.3.dist-info/LICENSE
pakkanpdf-0.1.3.dist-info/WHEEL
pakkanpdf-0.1.3.dist-info/METADATA
pakkanpdf-0.1.3.dist-info/RECORD
