Metadata-Version: 2.1
Name: pakkanpdf
Version: 0.1.3
Summary: pdf 内の text や image へのアクセスをコンテキストマネージャーを使ってシンプルに行える
Home-page: https://github.com/nnashiki/pakkan-pdf
Author: Niten Nashiki
Author-email: n.nashiki.work@gmail.com
Requires-Python: >=3.9,<4.0
Classifier: Programming Language :: Python :: 3
Classifier: Programming Language :: Python :: 3.10
Classifier: Programming Language :: Python :: 3.9
Requires-Dist: pdfminer.six[image] (>=20220524,<20220525)
Project-URL: Repository, https://github.com/nnashiki/pakkan-pdf
